blazee/__init__.py
blazee/client.py
blazee/keras_utils.py
blazee/lightgbm_utils.py
blazee/model.py
blazee/prediction.py
blazee/pytorch_utils.py
blazee/sklearn_utils.py
blazee/utils.py
blazee/xgboost_utils.py
tests/__init__.py
tests/conftest.py
tests/test_client.py
tests/test_model.py
tests/test_pipeline.py
blazee-0.1.5.dist-info/LICENSE
blazee-0.1.5.dist-info/METADATA
blazee-0.1.5.dist-info/NOTICE
blazee-0.1.5.dist-info/WHEEL
blazee-0.1.5.dist-info/top_level.txt
blazee-0.1.5.dist-info/RECORD
