Metadata-Version: 2.1
Name: blazee
Version: 0.1.5
Summary: Blazee makes it easy to deploy Machine Learning models on the cloud and turn them into an awesome prediction API.
Home-page: https://github.com/blazee-io/blazee-python
Author: blazee.io
Author-email: support@blazee.io
License: GNU General Public License v3.0
Platform: UNKNOWN
Classifier: Development Status :: 4 - Beta
Classifier: Intended Audience :: Developers
Classifier: Intended Audience :: Science/Research
Classifier: License :: OSI Approved :: GNU General Public License v3 (GPLv3)
Classifier: Natural Language :: English
Classifier: Operating System :: Microsoft :: Windows
Classifier: Operating System :: POSIX
Classifier: Operating System :: Unix
Classifier: Operating System :: MacOS
Classifier: Programming Language :: Python
Classifier: Programming Language :: Python :: 3
Classifier: Programming Language :: Python :: 3.5
Classifier: Programming Language :: Python :: 3.6
Classifier: Programming Language :: Python :: 3.7
Classifier: Topic :: Software Development
Classifier: Topic :: Scientific/Engineering
Requires-Dist: numpy
Requires-Dist: python-dateutil
Requires-Dist: requests
